{
    "$schema": "http://adaptivecards.io/schemas/adaptive-card.json",
    "type": "AdaptiveCard",
    "version": "1.2",
    "body": [
        {
            "type": "Container",
            "items": [
                {
                    "type": "TextBlock",
                    "text": "Server name",
                    "size": "extraLarge",
                    "wrap": true,
                    "weight": "bolder"
                },
                {
                    "type": "Container",
                    "items": [
                        {
                            "type": "TextBlock",
                            "text": " ",
                            "wrap": true
                        }
                    ]
                }
            ]
        },
        {
            "type": "Container",
            "spacing": "None",
            "items": [
                {
                    "type": "ColumnSet",
                    "columns": [
                        {
                            "type": "Column",
                            "width": "stretch",
                            "items": [
                                {
                                    "type": "TextBlock",
                                    "text": "CPU",
                                    "spacing": "None",
                                    "wrap": true,
                                    "size": "Medium"
                                },
                                {
                                    "type": "TextBlock",
                                    "text": "28 %",
                                    "color": "Good",
                                    "size": "ExtraLarge",
                                    "wrap": true
                                }
                            ]
                        },
                        {
                            "type": "Column",
                            "width": "auto",
                            "items": [
                                {
                                    "type": "Image",
                                    "url": "http://localhost:8080/img/pngegg.png",
                                    "width": "100px",
                                    "height": "100px"
                                }
                            ]
                        }
                    ]
                },
                {
                    "type": "ColumnSet",
                    "columns": [
                        {
                            "type": "Column",
                            "width": "stretch",
                            "items": [
                                {
                                    "type": "TextBlock",
                                    "text": "Memory",
                                    "spacing": "None",
                                    "wrap": true,
                                    "size": "Medium"
                                },
                                {
                                    "type": "TextBlock",
                                    "text": "85%",
                                    "color": "Attention",
                                    "size": "ExtraLarge",
                                    "wrap": true
                                }
                            ]
                        },
                        {
                            "type": "Column",
                            "width": "auto",
                            "items": [
                                {
                                    "type": "Image",
                                    "url": "http://localhost:8080/img/pngegg.png",
                                    "width": "100px",
                                    "height": "100px"
                                }
                            ]
                        }
                    ]
                },
                {
                    "type": "ColumnSet",
                    "columns": [
                        {
                            "type": "Column",
                            "width": "stretch",
                            "items": [
                                {
                                    "type": "TextBlock",
                                    "text": "Stroage",
                                    "spacing": "None",
                                    "wrap": true,
                                    "size": "Medium"
                                },
                                {
                                    "type": "TextBlock",
                                    "text": "61%",
                                    "color": "Warning",
                                    "size": "ExtraLarge",
                                    "wrap": true
                                }
                            ]
                        },
                        {
                            "type": "Column",
                            "width": "auto",
                            "items": [
                                {
                                    "type": "Image",
                                    "url": "http://localhost:8080/img/pngegg.png",
                                    "width": "100px",
                                    "height": "100px"
                                }
                            ]
                        }
                    ]
                },
                {
                    "type": "ColumnSet",
                    "columns": [
                        {
                            "type": "Column",
                            "width": "stretch",
                            "items": [
                                {
                                    "type": "TextBlock",
                                    "text": "HTTP Connections",
                                    "spacing": "None",
                                    "wrap": true,
                                    "size": "Medium"
                                },
                                {
                                    "type": "TextBlock",
                                    "text": "27",
                                    "color": "Good",
                                    "size": "ExtraLarge",
                                    "wrap": true
                                }
                            ]
                        },
                        {
                            "type": "Column",
                            "width": "auto",
                            "items": [
                                {
                                    "type": "Image",
                                    "url": "http://localhost:8080/img/pngegg.png",
                                    "width": "100px",
                                    "height": "100px"
                                }
                            ]
                        }
                    ]
                },
                {
                    "type": "ColumnSet",
                    "columns": [
                        {
                            "type": "Column",
                            "width": "stretch",
                            "items": [
                                {
                                    "type": "TextBlock",
                                    "text": "Database Connections",
                                    "spacing": "None",
                                    "wrap": true,
                                    "size": "Medium"
                                },
                                {
                                    "type": "TextBlock",
                                    "text": "15",
                                    "color": "Good",
                                    "size": "ExtraLarge",
                                    "wrap": true
                                }
                            ]
                        },
                        {
                            "type": "Column",
                            "width": "auto",
                            "items": [
                                {
                                    "type": "Image",
                                    "url": "http://localhost:8080/img/pngegg.png",
                                    "width": "100px",
                                    "height": "100px"
                                }
                            ]
                        }
                    ]
                }
            ]
        }
    ],
    "actions": [
        {
            "type": "Action.OpenUrl",
            "title": "View Info",
            "url": "http://localhost:8080/img/pngegg.png",
            "style": "positive"
        }
    ]
}